docker_auto_labels-0.2.4.dist-info/METADATA
docker_auto_labels-0.2.4.dist-info/WHEEL
docker_auto_labels-0.2.4.dist-info/entry_points.txt
docker_auto_labels-0.2.4.dist-info/licenses/LICENSE
docker_auto_labels/__init__.py
docker_auto_labels/cli.py
docker_auto_labels/docker_auto_labels.py
docker_auto_labels-0.2.4.dist-info/RECORD
