Metadata-Version: 2.1
Name: docker-auto-labels
Version: 0.2.4
Summary: Automatically generate Docker Swarm mode node labels for each constraint label in each service in a Docker Compose / Docker Stack file.
Author-Email: =?utf-8?q?Sebasti=C3=A1n_Ram=C3=ADrez?= <tiangolo@gmail.com>
Classifier: Development Status :: 2 - Pre-Alpha
Classifier: Intended Audience :: Developers
Classifier: License :: OSI Approved :: MIT License
Classifier: Programming Language :: Python :: 3
Project-URL: Homepage, https://github.com/tiangolo/docker-auto-labels
Requires-Python: >=3.8
Requires-Dist: click>=6.0
Requires-Dist: docker
Requires-Dist: pyyaml
